[
    {
        "title": "Business Card",
        "category": "WEB APP",
        "link": "https://anasbuildingwebsites.github.io/farish-business-card/",
        "img": "assets/business.png"
    },
    {
        "title": "Math Quiz",
        "category": "SYSTEM DESIGN",
        "link": "http://farish2010.github.io/Quiz-Game/",
        "img": "assets/quiz.png"
    },
    {
        "title": "Mars",
        "category": "DATA TOOL",
        "link": "https://anasbuildingwebsites.github.io/farish-fed-0111/",
        "img": "assets/mars.png"
    }
]